{
  "isAvailableForNewContent" : true,
  "templateType" : 6,
  "attachedStylesheets" : [ {
    "type" : "cos_extension_resource",
    "path" : "/AssetBank_March2019 Theme/Coded Files/AssetBank_March2019-style.css"
  } ],
  "attachedJs" : [ {
    "type" : "cos_extension_resource",
    "path" : "/AssetBank_March2019 Theme/Coded Files/AssetBank_March2019-main.js"
  } ],
  "customHead" : "",
  "customFooter" : "",
  "bodyClass" : "blog case-study-blog",
  "bodyCss" : "",
  "bodyEditable" : false,
  "layoutData" : {
    "x" : 0,
    "w" : 12,
    "name" : "",
    "label" : "",
    "type" : "cell",
    "params" : { },
    "rows" : [ {
      "0" : {
        "x" : 0,
        "w" : 12,
        "name" : "module_1601961793936336",
        "label" : "Mega Menu",
        "type" : "custom_widget",
        "params" : {
          "css_class" : "",
          "css_id" : "",
          "css_id_str" : "",
          "css_style" : "",
          "wrapping_html" : "",
          "per_widget_wrapper_html" : "",
          "overrideable" : true,
          "widget_name" : "Mega Menu",
          "schema_version" : 2,
          "path" : "/AssetBank_March2019 Theme/Custom Modules/Mega Menu"
        },
        "rows" : [ ],
        "rowMetaData" : [ ],
        "cells" : [ ],
        "cssId" : "",
        "cssClass" : "",
        "cssStyle" : "",
        "styles" : null,
        "widgets" : [ ]
      }
    }, {
      "0" : {
        "x" : 0,
        "w" : 12,
        "name" : "",
        "label" : "",
        "type" : "section_delimiter",
        "params" : {
          "cell" : false,
          "cells" : [ ],
          "css_class" : "",
          "css_id" : "",
          "css_id_str" : "",
          "css_style" : "",
          "ending_html" : "",
          "root" : false,
          "row" : false,
          "starting_html" : ""
        },
        "rows" : [ ],
        "rowMetaData" : [ ],
        "cells" : [ ],
        "cssId" : "",
        "cssClass" : "",
        "cssStyle" : "",
        "styles" : null,
        "widgets" : [ ]
      }
    }, {
      "0" : {
        "x" : 0,
        "w" : 12,
        "name" : "module_1551850699838585",
        "label" : "Sub Header - AssetBank_March2019 Theme",
        "type" : "custom_widget",
        "params" : {
          "css_class" : "",
          "css_id" : "",
          "css_id_str" : "",
          "css_style" : "",
          "item" : [ {
            "image" : {
              "alt" : "AssetBank",
              "height" : 75,
              "src" : "https://cdn2.hubspot.net/hubfs/4056449/AssetBank_March2019%20Theme/Images/AssetBank_Logo_Rev.svg",
              "width" : 300
            },
            "menu" : 7950848448
          } ],
          "overrideable" : false,
          "path" : "/AssetBank_March2019 Theme/Custom Modules/Sub Header - AssetBank_March2019 Theme",
          "per_widget_wrapper_html" : "",
          "schema_version" : 2,
          "show_menu" : true,
          "widget_name" : "Sub Header - AssetBank_March2019 Theme",
          "wrapping_html" : ""
        },
        "rows" : [ ],
        "rowMetaData" : [ ],
        "cells" : [ ],
        "cssId" : "",
        "cssClass" : "",
        "cssStyle" : "",
        "styles" : null,
        "widgets" : [ ]
      }
    }, {
      "0" : {
        "x" : 0,
        "w" : 12,
        "name" : "module_1551850486702497",
        "label" : "Case Study Post Banner Area - AssetBank_March2019 Theme",
        "type" : "custom_widget",
        "params" : {
          "css_class" : "",
          "css_id" : "",
          "css_id_str" : "",
          "css_style" : "",
          "overrideable" : true,
          "path" : "/AssetBank_March2019 Theme/Custom Modules/Case Study Post Banner Area - AssetBank_March2019 Theme",
          "per_widget_wrapper_html" : "",
          "schema_version" : 2,
          "widget_name" : "Case Study Post Banner Area - AssetBank_March2019 Theme",
          "wrapping_html" : ""
        },
        "rows" : [ ],
        "rowMetaData" : [ ],
        "cells" : [ ],
        "cssId" : "",
        "cssClass" : "",
        "cssStyle" : "",
        "styles" : null,
        "widgets" : [ ]
      }
    }, {
      "0" : {
        "x" : 0,
        "w" : 12,
        "name" : "module_1552280255613414",
        "label" : "Case Studies - Post Title - AssetBank_March2019 Theme",
        "type" : "custom_widget",
        "params" : {
          "css_class" : "",
          "css_id" : "",
          "css_id_str" : "",
          "css_style" : "",
          "overrideable" : true,
          "path" : "/AssetBank_March2019 Theme/Custom Modules/Case Studies - Post Title - AssetBank_March2019 Theme",
          "per_widget_wrapper_html" : "",
          "schema_version" : 2,
          "widget_name" : "Case Studies - Post Title - AssetBank_March2019 Theme",
          "wrapping_html" : ""
        },
        "rows" : [ ],
        "rowMetaData" : [ ],
        "cells" : [ ],
        "cssId" : "",
        "cssClass" : "",
        "cssStyle" : "",
        "styles" : null,
        "widgets" : [ ]
      }
    }, {
      "0" : {
        "x" : 0,
        "w" : 12,
        "name" : "module_1552280526228516",
        "label" : "Case Studies - Post Listing - AssetBank_March2019 Theme",
        "type" : "custom_widget",
        "params" : {
          "css_class" : "",
          "css_id" : "",
          "css_id_str" : "",
          "css_style" : "",
          "overrideable" : true,
          "path" : "/AssetBank_March2019 Theme/Custom Modules/Case Studies - Post Listing - AssetBank_March2019 Theme",
          "per_widget_wrapper_html" : "",
          "schema_version" : 2,
          "widget_name" : "Case Studies - Post Listing - AssetBank_March2019 Theme",
          "wrapping_html" : ""
        },
        "rows" : [ ],
        "rowMetaData" : [ ],
        "cells" : [ ],
        "cssId" : "",
        "cssClass" : "",
        "cssStyle" : "",
        "styles" : null,
        "widgets" : [ ]
      }
    }, {
      "0" : {
        "x" : 0,
        "w" : 12,
        "name" : "module_13885129496421879",
        "label" : "Page Center, Content Wrapper",
        "type" : "cell",
        "params" : {
          "cell" : false,
          "cells" : [ ],
          "css_class" : "page-center content-wrapper",
          "css_id" : "",
          "css_id_str" : "",
          "css_style" : "",
          "ending_html" : "",
          "overrideable" : false,
          "root" : false,
          "row" : false,
          "starting_html" : "",
          "value" : "",
          "wrapping_html" : ""
        },
        "rows" : [ {
          "0" : {
            "x" : 0,
            "w" : 8,
            "name" : "deduplicated_cell_138851284969979",
            "label" : "Blog Content",
            "type" : "cell",
            "params" : {
              "cell" : false,
              "cells" : [ ],
              "css_class" : "blog-content",
              "css_id" : "",
              "css_id_str" : "",
              "css_style" : "",
              "ending_html" : "",
              "overrideable" : false,
              "root" : false,
              "row" : false,
              "starting_html" : "",
              "value" : "",
              "wrapping_html" : ""
            },
            "rows" : [ {
              "0" : {
                "x" : 0,
                "w" : 12,
                "name" : "module_1523032069834331",
                "label" : "Blog Content",
                "type" : "custom_widget",
                "params" : {
                  "blog_listing_source" : "<!-- this blog uses separate master template for Listing/Post page  --> ",
                  "blog_post_source" : "<div class=\"blog-section\">\n  <div class=\"blog-post-wrapper cell-wrapper\">\n    <div class=\"section post-body\">\n      {{ content.post_body }}\n    </div>\n  </div>\n</div>\n<!-- Optional: Blog Author Bio Box -->\n{#<div class=\"about-author-sec row-fluid\">\n            <div class=\"span2\">\n                <img alt=\"{{ content.blog_post_author.display_name }}\" src=\"{{ content.blog_post_author.avatar }}\">\n            </div>\n            <div class=\"span10\">\n                <h3>Written by <a class=\"author-link\" href=\"{{ blog_author_url(group.id, content.blog_post_author.slug) }}\">{{ content.blog_post_author.display_name }}</a></h3>\n                <p>{{ content.blog_post_author.bio }}</p>\n                {% if content.blog_post_author.has_social_profiles %}\n                    <div class=\"hs-author-social-section\">\n                        <div class=\"hs-author-social-links\">\n                            {% if content.blog_post_author.facebook %}\n                                <a href=\"{{ content.blog_post_author.facebook }}\" target=\"_blank\" class=\"hs-author-social-link hs-social-facebook\">Facebook</a>\n                            {% endif %}\n                            {% if content.blog_post_author.linkedin %}\n                                <a href=\"{{ content.blog_post_author.linkedin }}\" target=\"_blank\" class=\"hs-author-social-link hs-social-linkedin\">LinkedIn</a>\n                            {% endif %}\n                            {% if content.blog_post_author.twitter %}\n                                <a href=\"{{ content.blog_post_author.twitter }}\" target=\"_blank\" class=\"hs-author-social-link hs-social-twitter\">Twitter</a>\n                            {% endif %}\n                            {% if content.blog_post_author.google_plus %}\n                                <a href=\"{{ content.blog_post_author.google_plus }}?rel=author\" target=\"_blank\" class=\"hs-author-social-link hs-social-google-plus\">Google+</a>\n                            {% endif %}\n                        </div>\n                    </div>\n                {% endif %}\n            </div>\n        </div>#}",
                  "css_class" : "",
                  "css_id" : "",
                  "css_id_str" : "",
                  "css_style" : "",
                  "overrideable" : false,
                  "path" : "@hubspot/blog_content",
                  "per_widget_wrapper_html" : "",
                  "schema_version" : 2,
                  "template_to_edit" : "post",
                  "widget_name" : "Blog Content",
                  "wrapping_html" : ""
                },
                "rows" : [ ],
                "rowMetaData" : [ ],
                "cells" : [ ],
                "cssId" : "",
                "cssClass" : "",
                "cssStyle" : "",
                "styles" : null,
                "widgets" : [ ]
              }
            }, {
              "0" : {
                "x" : 0,
                "w" : 12,
                "name" : "module_155185733696074",
                "label" : "Video - AssetBank_March2019 Theme",
                "type" : "custom_widget",
                "params" : {
                  "css_class" : "",
                  "css_id" : "",
                  "css_id_str" : "",
                  "css_style" : "",
                  "overrideable" : true,
                  "path" : "/AssetBank_March2019 Theme/Custom Modules/Video - AssetBank_March2019 Theme",
                  "per_widget_wrapper_html" : "",
                  "schema_version" : 2,
                  "widget_name" : "Video - AssetBank_March2019 Theme",
                  "wrapping_html" : ""
                },
                "rows" : [ ],
                "rowMetaData" : [ ],
                "cells" : [ ],
                "cssId" : "",
                "cssClass" : "",
                "cssStyle" : "",
                "styles" : null,
                "widgets" : [ ]
              }
            }, {
              "0" : {
                "x" : 0,
                "w" : 12,
                "name" : "module_1523032063950328",
                "label" : "Blog Comments",
                "type" : "custom_widget",
                "params" : {
                  "css_class" : "",
                  "css_id" : "",
                  "css_id_str" : "",
                  "css_style" : "",
                  "overrideable" : false,
                  "path" : "@hubspot/blog_comments",
                  "per_widget_wrapper_html" : "",
                  "schema_version" : 2,
                  "widget_name" : "Blog Comments",
                  "wrapping_html" : ""
                },
                "rows" : [ ],
                "rowMetaData" : [ ],
                "cells" : [ ],
                "cssId" : "",
                "cssClass" : "",
                "cssStyle" : "",
                "styles" : null,
                "widgets" : [ ]
              }
            } ],
            "rowMetaData" : [ ],
            "cells" : [ ],
            "cssId" : "",
            "cssClass" : "blog-content",
            "cssStyle" : "",
            "styles" : null,
            "widgets" : [ ]
          },
          "8" : {
            "x" : 8,
            "w" : 4,
            "name" : "migrated_unnamed_cell_138851284969980",
            "label" : "Blog Sidebar",
            "type" : "cell",
            "params" : {
              "cell" : false,
              "cells" : [ ],
              "css_class" : "blog-sidebar",
              "css_id" : "",
              "css_id_str" : "",
              "css_style" : "",
              "ending_html" : "",
              "overrideable" : false,
              "root" : false,
              "row" : false,
              "starting_html" : "",
              "value" : "",
              "wrapping_html" : ""
            },
            "rows" : [ {
              "0" : {
                "x" : 0,
                "w" : 12,
                "name" : "module_1551850674262581",
                "label" : "Resource Centre - AssetBank_March2019 Theme",
                "type" : "custom_widget",
                "params" : {
                  "css_class" : "",
                  "css_id" : "",
                  "css_id_str" : "",
                  "css_style" : "",
                  "overrideable" : false,
                  "path" : "/AssetBank_March2019 Theme/Custom Modules/Resource Centre - AssetBank_March2019 Theme",
                  "per_widget_wrapper_html" : "",
                  "schema_version" : 2,
                  "widget_name" : "Resource Centre - AssetBank_March2019 Theme",
                  "wrapping_html" : ""
                },
                "rows" : [ ],
                "rowMetaData" : [ ],
                "cells" : [ ],
                "cssId" : "",
                "cssClass" : "",
                "cssStyle" : "",
                "styles" : null,
                "widgets" : [ ]
              }
            } ],
            "rowMetaData" : [ ],
            "cells" : [ ],
            "cssId" : "",
            "cssClass" : "blog-sidebar",
            "cssStyle" : "",
            "styles" : null,
            "widgets" : [ ]
          }
        } ],
        "rowMetaData" : [ ],
        "cells" : [ ],
        "cssId" : "",
        "cssClass" : "page-center content-wrapper",
        "cssStyle" : "",
        "styles" : null,
        "widgets" : [ ]
      }
    }, {
      "0" : {
        "x" : 0,
        "w" : 12,
        "name" : "module_1551850689615583",
        "label" : "Book Your Demo - AssetBank_March2019 Theme",
        "type" : "custom_widget",
        "params" : {
          "css_class" : "",
          "css_id" : "",
          "css_id_str" : "",
          "css_style" : "",
          "overrideable" : true,
          "path" : "/AssetBank_March2019 Theme/Custom Modules/Book Your Demo - AssetBank_March2019 Theme",
          "per_widget_wrapper_html" : "",
          "schema_version" : 2,
          "widget_name" : "Book Your Demo - AssetBank_March2019 Theme",
          "wrapping_html" : ""
        },
        "rows" : [ ],
        "rowMetaData" : [ ],
        "cells" : [ ],
        "cssId" : "",
        "cssClass" : "",
        "cssStyle" : "",
        "styles" : null,
        "widgets" : [ ]
      }
    }, {
      "0" : {
        "x" : 0,
        "w" : 12,
        "name" : "",
        "label" : "",
        "type" : "section_delimiter",
        "params" : {
          "cell" : false,
          "cells" : [ ],
          "css_class" : "",
          "css_id" : "",
          "css_id_str" : "",
          "css_style" : "",
          "ending_html" : "",
          "root" : false,
          "row" : false,
          "starting_html" : ""
        },
        "rows" : [ ],
        "rowMetaData" : [ ],
        "cells" : [ ],
        "cssId" : "",
        "cssClass" : "",
        "cssStyle" : "",
        "styles" : null,
        "widgets" : [ ]
      }
    }, {
      "0" : {
        "x" : 0,
        "w" : 12,
        "name" : "HubSpot_Boilerplate Theme/Footer",
        "label" : "HubSpot_Boilerplate Theme/Footer",
        "type" : "global_group",
        "params" : {
          "cell" : false,
          "cells" : [ ],
          "css_class" : "",
          "css_id" : "",
          "css_id_str" : "",
          "css_style" : "",
          "ending_html" : "",
          "overrideable" : false,
          "path" : "/AssetBank_March2019 Theme/Global Groups/AssetBank_March2019 Footer.template.json",
          "root" : false,
          "row" : false,
          "starting_html" : ""
        },
        "rows" : [ ],
        "rowMetaData" : [ ],
        "cells" : [ ],
        "cssId" : "",
        "cssClass" : "",
        "cssStyle" : "",
        "styles" : null,
        "widgets" : [ ]
      }
    } ],
    "rowMetaData" : [ ],
    "cells" : [ ],
    "cssId" : "",
    "cssClass" : "",
    "cssStyle" : "",
    "styles" : null,
    "widgets" : [ ]
  }
}