{
  "isAvailableForNewContent" : true,
  "templateType" : 4,
  "attachedStylesheets" : [ {
    "type" : "cos_extension_resource",
    "path" : "/AssetBank_March2019 Theme/Coded Files/AssetBank_March2019-style.css"
  } ],
  "attachedJs" : [ {
    "type" : "cos_extension_resource",
    "path" : "/AssetBank_March2019 Theme/Coded Files/AssetBank_March2019-main.js"
  } ],
  "customHead" : "",
  "customFooter" : "",
  "bodyClass" : "site-page one-column hs-book-a-demo",
  "bodyCss" : "",
  "bodyEditable" : false,
  "layoutData" : {
    "x" : 0,
    "w" : 12,
    "name" : "",
    "label" : "",
    "type" : "cell",
    "params" : { },
    "rows" : [ {
      "0" : {
        "x" : 0,
        "w" : 12,
        "name" : "module_161048733136129",
        "label" : "AssetBank_March2019 Header-Bright",
        "type" : "global_group",
        "params" : {
          "css_class" : "",
          "css_id" : "",
          "css_id_str" : "",
          "css_style" : "",
          "wrapping_html" : "",
          "per_widget_wrapper_html" : "",
          "overrideable" : false,
          "path" : "/AssetBank_March2019 Theme/Global Groups/AssetBank_March2019 Header-Bright.template.json"
        },
        "rows" : [ ],
        "rowMetaData" : [ ],
        "cells" : [ ],
        "cssId" : "",
        "cssClass" : "",
        "cssStyle" : "",
        "styles" : null,
        "widgets" : [ ]
      }
    }, {
      "0" : {
        "x" : 0,
        "w" : 12,
        "name" : "",
        "label" : "",
        "type" : "section_delimiter",
        "params" : {
          "cell" : false,
          "cells" : [ ],
          "css_class" : "",
          "css_id" : "",
          "css_id_str" : "",
          "css_style" : "",
          "ending_html" : "",
          "root" : false,
          "row" : false,
          "starting_html" : ""
        },
        "rows" : [ ],
        "rowMetaData" : [ ],
        "cells" : [ ],
        "cssId" : "",
        "cssClass" : "",
        "cssStyle" : "",
        "styles" : null,
        "widgets" : [ ]
      }
    }, {
      "0" : {
        "x" : 0,
        "w" : 12,
        "name" : "module_15518682754221231",
        "label" : "Site Content",
        "type" : "cell",
        "params" : {
          "css_class" : "site-content",
          "css_id" : "",
          "css_id_str" : "",
          "css_style" : "",
          "overrideable" : false,
          "per_widget_wrapper_html" : "",
          "wrapping_html" : ""
        },
        "rows" : [ {
          "0" : {
            "x" : 0,
            "w" : 12,
            "name" : "module_15518658109121008",
            "label" : "Banner Area with Form - AssetBank_March2019 Theme",
            "type" : "custom_widget",
            "params" : {
              "css_class" : "",
              "css_id" : "",
              "css_id_str" : "",
              "css_style" : "",
              "overrideable" : true,
              "path" : "/AssetBank_March2019 Theme/Custom Modules/Banner Area with Form - AssetBank_March2019 Theme",
              "per_widget_wrapper_html" : "",
              "schema_version" : 2,
              "widget_name" : "Banner Area with Form - AssetBank_March2019 Theme",
              "wrapping_html" : ""
            },
            "rows" : [ ],
            "rowMetaData" : [ ],
            "cells" : [ ],
            "cssId" : "",
            "cssClass" : "",
            "cssStyle" : "",
            "styles" : null,
            "widgets" : [ ]
          }
        }, {
          "0" : {
            "x" : 0,
            "w" : 12,
            "name" : "module_15518660879031140",
            "label" : "Client Logos Group - AssetBank_March2019 Theme",
            "type" : "custom_widget",
            "params" : {
              "css_class" : "",
              "css_id" : "",
              "css_id_str" : "",
              "css_style" : "",
              "overrideable" : true,
              "path" : "/AssetBank_March2019 Theme/Custom Modules/Client Logos Group - AssetBank_March2019 Theme",
              "per_widget_wrapper_html" : "",
              "schema_version" : 2,
              "widget_name" : "Client Logos Group - AssetBank_March2019 Theme",
              "wrapping_html" : ""
            },
            "rows" : [ ],
            "rowMetaData" : [ ],
            "cells" : [ ],
            "cssId" : "",
            "cssClass" : "",
            "cssStyle" : "",
            "styles" : null,
            "widgets" : [ ]
          }
        } ],
        "rowMetaData" : [ ],
        "cells" : [ ],
        "cssId" : "",
        "cssClass" : "site-content",
        "cssStyle" : "",
        "styles" : null,
        "widgets" : [ ]
      }
    }, {
      "0" : {
        "x" : 0,
        "w" : 12,
        "name" : "",
        "label" : "",
        "type" : "section_delimiter",
        "params" : {
          "cell" : false,
          "cells" : [ ],
          "css_class" : "",
          "css_id" : "",
          "css_id_str" : "",
          "css_style" : "",
          "ending_html" : "",
          "root" : false,
          "row" : false,
          "starting_html" : ""
        },
        "rows" : [ ],
        "rowMetaData" : [ ],
        "cells" : [ ],
        "cssId" : "",
        "cssClass" : "",
        "cssStyle" : "",
        "styles" : null,
        "widgets" : [ ]
      }
    }, {
      "0" : {
        "x" : 0,
        "w" : 12,
        "name" : "module_1551865304008775",
        "label" : "AssetBank_March2019 Footer-AssetBank",
        "type" : "global_group",
        "params" : {
          "css_class" : "",
          "css_id" : "",
          "css_id_str" : "",
          "css_style" : "",
          "overrideable" : false,
          "path" : "/AssetBank_March2019 Theme/Global Groups/AssetBank_March2019 Footer-AssetBank.template.json",
          "per_widget_wrapper_html" : "",
          "wrapping_html" : ""
        },
        "rows" : [ ],
        "rowMetaData" : [ ],
        "cells" : [ ],
        "cssId" : "",
        "cssClass" : "",
        "cssStyle" : "",
        "styles" : null,
        "widgets" : [ ]
      }
    } ],
    "rowMetaData" : [ ],
    "cells" : [ ],
    "cssId" : "",
    "cssClass" : "",
    "cssStyle" : "",
    "styles" : null,
    "widgets" : [ ]
  }
}